setup.py
pytest_encode/__init__.py
pytest_encode.egg-info/PKG-INFO
pytest_encode.egg-info/SOURCES.txt
pytest_encode.egg-info/dependency_links.txt
pytest_encode.egg-info/entry_points.txt
pytest_encode.egg-info/not-zip-safe
pytest_encode.egg-info/requires.txt
pytest_encode.egg-info/top_level.txt